{"app_permissions::name='android_permission_INTERNET'":1,"app_permissions::name='android_permission_RECORD_AUDIO'":1,"app_permissions::name='android_permission_MODIFY_AUDIO_SETTINGS'":1,"app_permissions::name='android_permission_READ_PHONE_STATE'":1,"app_permissions::name='android_permission_WRITE_EXTERNAL_STORAGE'":1,"app_permissions::name='android_permission_READ_EXTERNAL_STORAGE'":1,"app_permissions::name='android_permission_ACCESS_NETWORK_STATE'":1,"app_permissions::name='android_permission_ACCESS_WIFI_STATE'":1,"app_permissions::name='android_permission_RECEIVE_BOOT_COMPLETED'":1,"app_permissions::name='android_permission_CHANGE_NETWORK_STATE'":1,"app_permissions::name='android_permission_READ_CONTACTS'":1,"app_permissions::name='android_permission_WRITE_SETTINGS'":1,"app_permissions::name='android_permission_ACCESS_COARSE_LOCATION'":1,"app_permissions::name='android_permission_ACCESS_FINE_LOCATION'":1,"app_permissions::name='android_permission_ACCESS_LOCATION_EXTRA_COMMANDS'":1,"app_permissions::name='android_permission_ACCESS_GPS'":1,"app_permissions::name='android_permission_CAMERA'":1,"app_permissions::name='com_sec_android_provider_badge_permission_READ'":1,"app_permissions::name='com_sec_android_provider_badge_permission_WRITE'":1,"app_permissions::name='com_htc_launcher_permission_READ_SETTINGS'":1,"app_permissions::name='com_htc_launcher_permission_UPDATE_SHORTCUT'":1,"app_permissions::name='com_sonyericsson_home_permission_BROADCAST_BADGE'":1,"app_permissions::name='com_sonymobile_home_permission_PROVIDER_INSERT_BADGE'":1,"app_permissions::name='com_anddoes_launcher_permission_UPDATE_COUNT'":1,"app_permissions::name='com_majeur_launcher_permission_UPDATE_BADGE'":1,"app_permissions::name='com_huawei_android_launcher_permission_CHANGE_BADGE'":1,"app_permissions::name='com_huawei_android_launcher_permission_READ_SETTINGS'":1,"app_permissions::name='com_huawei_android_launcher_permission_WRITE_SETTINGS'":1,"app_permissions::name='android_permission_READ_APP_BADGE'":1,"app_permissions::name='com_oppo_launcher_permission_READ_SETTINGS'":1,"app_permissions::name='com_oppo_launcher_permission_WRITE_SETTINGS'":1,"app_permissions::name='me_everything_badger_permission_BADGE_COUNT_READ'":1,"app_permissions::name='me_everything_badger_permission_BADGE_COUNT_WRITE'":1,"api_permissions::android_permission_WAKE_LOCK":1,"api_permissions::android_permission_VIBRATE":1,"api_permissions::android_permission_READ_CONTACTS":1,"api_permissions::android_permission_ACCESS_NETWORK_STATE":1,"api_permissions::android_permission_INTERNET":1,"api_permissions::android_permission_RECORD_AUDIO":1,"api_permissions::android_permission_WRITE_SETTINGS":1,"api_permissions::android_permission_READ_LOGS":1,"api_permissions::android_permission_GET_TASKS":1,"api_permissions::android_permission_ACCESS_FINE_LOCATION":1,"api_permissions::android_permission_MODIFY_AUDIO_SETTINGS":1,"api_permissions::android_permission_ACCESS_WIFI_STATE":1,"api_permissions::android_permission_READ_PHONE_STATE":1,"api_permissions::android_permission_CHANGE_WIFI_STATE":1,"api_permissions::android_permission_CAMERA":1,"api_calls::android\/app\/Activity;->startActivity":1,"api_calls::android\/app\/Activity;->startActivityForResult":1,"api_calls::android\/content\/Context;->startActivity":1,"api_calls::android\/content\/Context;->startService":1,"api_calls::android\/os\/PowerManager$WakeLock;->acquire":1,"api_calls::android\/os\/PowerManager$WakeLock;->release":1,"api_calls::android\/app\/NotificationManager;->notify":1,"api_calls::android\/content\/ContentResolver;->query":1,"api_calls::android\/content\/Context;->sendBroadcast":1,"api_calls::android\/content\/Context;->sendOrderedBroadcast":1,"api_calls::android\/content\/ContentResolver;->openFileDescriptor":1,"api_calls::android\/content\/ContentResolver;->openInputStream":1,"api_calls::android\/net\/ConnectivityManager;->getActiveNetworkInfo":1,"api_calls::android\/net\/ConnectivityManager;->getNetworkInfo":1,"api_calls::java\/net\/DatagramSocket":1,"api_calls::java\/net\/Socket":1,"api_calls::android\/webkit\/WebView":1,"api_calls::java\/net\/HttpURLConnection":1,"api_calls::java\/net\/URL;->openConnection":1,"api_calls::java\/net\/HttpURLConnection;->connect":1,"api_calls::android\/media\/MediaPlayer;->start":1,"api_calls::android\/media\/MediaRecorder;->setAudioSource":1,"api_calls::android\/media\/AudioRecord":1,"api_calls::android\/net\/ConnectivityManager;->getAllNetworkInfo":1,"api_calls::android\/net\/NetworkInfo;->isConnectedOrConnecting":1,"api_calls::android\/provider\/Settings$System;->putString":1,"api_calls::java\/lang\/Runtime;->exec":1,"api_calls::android\/app\/ActivityManager;->getRecentTasks":1,"api_calls::android\/telephony\/TelephonyManager;->getCellLocation":1,"api_calls::android\/media\/AudioManager;->setBluetoothScoOn":1,"api_calls::android\/media\/AudioManager;->startBluetoothSco":1,"api_calls::android\/media\/AudioManager;->stopBluetoothSco":1,"api_calls::android\/net\/wifi\/WifiManager;->getConnectionInfo":1,"api_calls::android\/net\/wifi\/WifiManager;->getScanResults":1,"api_calls::android\/net\/wifi\/WifiManager;->isWifiEnabled":1,"api_calls::android\/telephony\/TelephonyManager;->getDeviceId":1,"api_calls::android\/telephony\/TelephonyManager;->getSubscriberId":1,"api_calls::java\/net\/NetworkInterface":1,"api_calls::android\/location\/LocationManager;->getBestProvider":1,"api_calls::android\/location\/LocationManager;->getLastKnownLocation":1,"api_calls::android\/location\/LocationManager;->getProvider":1,"api_calls::android\/location\/LocationManager;->getProviders":1,"api_calls::android\/location\/LocationManager;->isProviderEnabled":1,"api_calls::org\/apache\/http\/impl\/client\/DefaultHttpClient":1,"api_calls::org\/apache\/http\/impl\/client\/DefaultHttpClient;->execute":1,"api_calls::android\/telephony\/TelephonyManager;->getSimSerialNumber":1,"api_calls::android\/net\/wifi\/WifiManager;->addNetwork":1,"api_calls::android\/net\/wifi\/WifiManager;->enableNetwork":1,"api_calls::android\/net\/wifi\/WifiManager;->getWifiState":1,"api_calls::android\/telephony\/TelephonyManager;->getNeighboringCellInfo":1,"api_calls::android\/telephony\/TelephonyManager;->listen":1,"api_calls::android\/location\/LocationManager;->addGpsStatusListener":1,"api_calls::android\/location\/LocationManager;->requestLocationUpdates":1,"api_calls::android\/telephony\/TelephonyManager;->getLine1Number":1,"api_calls::android\/net\/wifi\/WifiManager;->startScan":1,"api_calls::android\/hardware\/Camera;->open":1,"api_calls::android\/app\/Activity;->sendBroadcast":1,"api_calls::java\/net\/ServerSocket":1,"api_calls::android\/content\/ContentResolver;->openOutputStream":1,"api_calls::android\/webkit\/WebChromeClient;->onGeolocationPermissionsShowPrompt":1,"api_calls::java\/net\/URLConnection;->getInputStream":1,"api_calls::android\/media\/MediaPlayer;->stop":1,"activities::b'_MainActivity'":1,"interesting_calls::getSystemService":1,"interesting_calls::Read\/Write External Storage":1,"interesting_calls::Obfuscation(Base64)":1,"interesting_calls::getPackageInfo":1,"interesting_calls::printStackTrace":1,"interesting_calls::getCellLocation":1,"interesting_calls::getDeviceId":1,"interesting_calls::getSubscriberId":1,"interesting_calls::HttpPost":1,"interesting_calls::Cipher(AES\/ECB\/PKCS5Padding)":1,"interesting_calls::Cipher(RSA\/ECB\/PKCS1Padding)":1,"interesting_calls::getWifiState":1,"interesting_calls::Cipher(AES\/CBC\/PKCS7Padding)":1,"interesting_calls::Cipher(tlsVersion)":1,"interesting_calls::Cipher(Ljava\/lang\/Enum)":1,"interesting_calls::Cipher(Ljava\/util\/List)":1,"interesting_calls::Cipher(()":1,"urls::http:\/\/schemas_android_com\/apk\/res\/android":1,"urls::http:\/\/iss_openspeech_cn\/v?":1,"urls::http:\/\/dev_voicecloud_cn\/msc\/help_html\\":1,"urls::http:\/\/dev_voicecloud_cn\/msc\/help_html":1,"urls::http:\/\/scs_openspeech_cn\/scs":1,"urls::http:\/\/data_openspeech_cn\/index_php\/clientrequest\/clientcollect\/isCollect":1,"urls::http:\/\/openapi_openspeech_cn\/webapi\/wfr_do":1,"urls::http:\/\/www_xunfei_cn\/?appid=":1,"urls::http:\/\/iws_openspeech_cn\/online_param\/config_update_php":1,"urls::http:\/\/app_sina_cn\/appdetail_php?appID=84560":1,"urls::https:\/\/open_weibo_cn\/oauth2\/authorize?":1,"urls::http:\/\/weibo_cn\/dpool\/ttt\/maps_php?xy=%s,%s&amp;size=320x320&amp;offset=%s":1,"urls::http:\/\/api_weibo_cn\/2\/client\/common_config":1,"urls::https:\/\/api_weibo_com\/2\/proxy\/darwin\/graph\/game\/":1,"urls::http:\/\/widget_weibo_com\/invitation\/app_php?":1,"urls::http:\/\/widget_weibo_com\/invitation\/appinfo_php?":1,"urls::http:\/\/service_weibo_com\/share\/mobilesdk_php":1,"urls::http:\/\/service_weibo_com\/share\/mobilesdk_uppic_php":1,"urls::http:\/\/widget_weibo_com\/relationship\/followsdk_php":1,"urls::https:\/\/api_weibo_com\/2\/friendships\/show_json":1,"urls::http:\/\/widget_weibo_com\/distribution\/socail_comments_sdk_php":1,"urls::https:\/\/api_weibo_com\/oauth2\/access_token":1,"urls::https:\/\/api_weibo_com\/2\/statuses\/repost_json":1,"urls::https:\/\/api_weibo_com\/2\/statuses\/update_json":1,"urls::https:\/\/api_weibo_com\/2\/statuses\/upload_json":1,"urls::http:\/\/api_weibo_com\/oauth2\/sms_authorize\/send":1,"urls::http:\/\/api_weibo_com\/oauth2\/sms_authorize\/submit":1,"urls::http:\/\/m_weibo_cn\/reg\/privacyagreement?from=h5&wm=3349":1,"urls::http:\/\/weibo_cn\/dpool\/ttt\/h5\/regagreement_php?from=h5":1,"urls::http:\/\/weibo_cn\/dpool\/ttt\/h5\/regagreement_php?from=h5&lang=":1,"urls::http:\/\/m_weibo_cn\/reg\/privacyagreement?from=h5&wm=3349&lang=":1,"urls::https:\/\/api_weibo_com\/2\/proxy\/sdk\/statistic_json":1,"urls::https:\/\/api_weibo_com\/oauth2\/getaid_json":1,"urls::http:\/\/appsupport_qq_com\/cgi-bin\/qzapps\/mapp_addapp_cgi":1,"urls::http:\/\/openmobile_qq_com\/oauth2_0\/m_authorize?":1,"urls::https:\/\/openmobile_qq_com\/user\/user_login_statis":1,"urls::https:\/\/openmobile_qq_com\/v3\/user\/get_info":1,"urls::http:\/\/qzs_qq_com\/open\/mobile\/login\/qzsjump_html?":1,"urls::http:\/\/openmobile_qq_com\/oauth2_0\/m_jump_by_version?":1,"urls::https:\/\/openmobile_qq_com\/":1,"urls::http:\/\/fusion_qq_com\/cgi-bin\/qzapps\/unified_jump?appid=%1$s&from=%2$s&isOpenAppID=1":1,"urls::http:\/\/ls_map_soso_com\/deflect?c=1":1,"urls::http:\/\/lstest_map_soso_com\/loc?c=1":1,"urls::http:\/\/lbs_map_qq_com\/loc?c=1":1,"urls::http:\/\/ls_map_soso_com\/monitor\/monitor_html":1,"urls::http:\/\/fusion_qq_com\/cgi-bin\/prize_sharing\/make_share_url_cgi":1,"urls::http:\/\/fusion_qq_com\/cgi-bin\/prize_sharing\/query_unexchange_prize_cgi":1,"urls::http:\/\/fusion_qq_com\/cgi-bin\/prize_sharing\/exchange_prize_cgi":1,"urls::http:\/\/fusion_qq_com\/cgi-bin\/prize_sharing\/get_activity_state_cgi":1,"urls::http:\/\/fusion_qq_com\/cgi-bin\/qzapps\/mapp_lbs_getnear_cgi":1,"urls::http:\/\/fusion_qq_com\/cgi-bin\/qzapps\/mapp_lbs_delete_cgi":1,"urls::http:\/\/qzs_qq_com\/open\/mobile\/not_support_html?":1,"urls::http:\/\/qzs_qq_com\/open\/mobile\/request\/sdk_request_html?":1,"urls::http:\/\/qzs_qq_com\/open\/mobile\/brag\/sdk_brag_html?":1,"urls::http:\/\/qzs_qq_com\/open\/mobile\/rate\/sdk_rate_html?":1,"urls::http:\/\/qzs_qq_com\/open\/mobile\/invite\/sdk_invite_html?":1,"urls::http:\/\/qzs_qq_com\/open\/mobile\/reactive\/sdk_reactive_html?":1,"urls::http:\/\/qzs_qq_com\/open\/mobile\/sendstory\/sdk_sendstory_v1_3_html?":1,"urls::http:\/\/qzs_qq_com":1,"urls::http:\/\/appact_qzone_qq_com\/appstore_activity_task_pcpush_sdk":1,"urls::http:\/\/c_isdspeed_qq_com\/code_cgi":1,"urls::http:\/\/wspeed_qq_com\/w_cgi":1,"urls::http:\/\/appsupport_qq_com\/cgi-bin\/appstage\/mstats_batch_report":1,"urls::http:\/\/cgi_connect_qq_com\/qqconnectopen\/openapi\/policy_conf":1,"urls::http:\/\/fusion_qq_com\/cgi-bin\/qzapps\/mapp_getappinfo_cgi":1,"urls::http:\/\/qzs_qq_com\/open\/mobile\/sdk_common\/down_qq_htm?":1,"urls::http:\/\/fusion_qq_com":1,"urls::http:\/\/fusion_qq_com\/cgi-bin":1,"urls::http:\/\/cgi_qplus_com\/report\/report":1,"urls::http:\/\/webpresence_qq_com\/getonline?Type=1&":1,"urls::http:\/\/www_myapp_com\/forward\/a\/45592?g_f=990935":1,"urls::http:\/\/m_wsq_qq_com\/direct?":1,"urls::http:\/\/qzs_qq_com\/open\/mobile\/jsbridge\/demo_htm":1,"urls::http:\/\/analy_qq_com\/cgi-bin\/mapp_apptrace":1,"urls::http:\/\/pingma_qq_com:80\/mstat\/report":1,"urls::http:\/\/mta_qq_com\/":1,"urls::https:\/\/uop_umeng_com":1,"urls::http:\/\/alog_umeng_com\/app_logs":1,"urls::http:\/\/alog_umengcloud_com\/app_logs":1,"urls::https:\/\/cmnsguider_yunos_com:443\/genDeviceToken":1,"urls::http:\/\/log_umsns_com\/":1,"urls::http:\/\/log_umsns_com\/share\/api\/":1,"urls::https:\/\/dev_youbanban_com":1,"urls::https:\/\/app_youbanban_com\/gkiwi\/osvc\/image":1,"urls::https:\/\/dev3_youbanban_com":1,"urls::https:\/\/jsqy_youbanban_com":1,"urls::https:\/\/ssl_gstatic_com\/accessibility\/javascript\/android\/":1,"urls::http:\/\/*\/*":1,"urls::https:\/\/*\/*":1,"urls::https:\/\/api_weibo_com\/oauth2\/default_html":1,"urls::http:\/\/www_sinaimg_cn\/blog\/developer\/wiki\/LOGO_64x64_png":1}