{"app_permissions::name='android_permission_ACCESS_NETWORK_STATE'":1,"app_permissions::name='android_permission_ACCESS_FINE_LOCATION'":1,"app_permissions::name='android_permission_VIBRATE'":1,"app_permissions::name='android_permission_INTERNET'":1,"app_permissions::name='android_permission_WAKE_LOCK'":1,"app_permissions::name='com_google_android_c2dm_permission_RECEIVE'":1,"app_permissions::name='com_engrmbr_fiftycentworth_permission_C2D_MESSAGE'":1,"api_permissions::android_permission_WAKE_LOCK":1,"api_permissions::android_permission_INTERNET":1,"api_permissions::android_permission_VIBRATE":1,"api_permissions::android_permission_READ_CONTACTS":1,"api_permissions::android_permission_ACCESS_NETWORK_STATE":1,"api_calls::android\/content\/Context;->startService":1,"api_calls::android\/os\/PowerManager$WakeLock;->acquire":1,"api_calls::android\/os\/PowerManager$WakeLock;->release":1,"api_calls::android\/webkit\/WebView":1,"api_calls::android\/content\/Context;->startActivity":1,"api_calls::android\/app\/NotificationManager;->notify":1,"api_calls::java\/net\/HttpURLConnection":1,"api_calls::java\/net\/HttpURLConnection;->connect":1,"api_calls::java\/net\/URL;->openConnection":1,"api_calls::android\/content\/ContentResolver;->query":1,"api_calls::android\/net\/ConnectivityManager;->getActiveNetworkInfo":1,"api_calls::android\/content\/Context;->sendBroadcast":1,"activities::b'_MainActivity'":1,"interesting_calls::getSystemService":1,"interesting_calls::getPackageInfo":1,"interesting_calls::printStackTrace":1,"interesting_calls::Obfuscation(Base64)":1,"urls::http:\/\/play_google_com\/store\/apps\/details?id=":1,"urls::https:\/\/50centworth_com":1,"urls::https:\/\/pagead2_googlesyndication_com\/pagead\/gen_204?id=gmob-apps":1,"urls::https:\/\/goo_gl\/FZRIUV":1,"urls::https:\/\/app-measurement_com\/a":1}